sqlalchemy_oso/__init__.py
sqlalchemy_oso/auth.py
sqlalchemy_oso/compat.py
sqlalchemy_oso/flask.py
sqlalchemy_oso/oso.py
sqlalchemy_oso/partial.py
sqlalchemy_oso/preprocess.py
sqlalchemy_oso/py.typed
sqlalchemy_oso/session.py
sqlalchemy_oso/sqlalchemy_utils.py
sqlalchemy_oso-0.27.2.dist-info/METADATA
sqlalchemy_oso-0.27.2.dist-info/WHEEL
sqlalchemy_oso-0.27.2.dist-info/entry_points.txt
sqlalchemy_oso-0.27.2.dist-info/top_level.txt
sqlalchemy_oso-0.27.2.dist-info/RECORD
