Metadata-Version: 2.1
Name: sqlalchemy-oso
Version: 0.27.2
Summary: oso sqlalchemy integration
Home-page: UNKNOWN
Author: Oso Security, Inc.
Author-email: support@osohq.com
License: UNKNOWN
Project-URL: Source, https://github.com/osohq/oso/tree/main/languages/python/sqlalchemy-oso
Platform: UNKNOWN
Classifier: Development Status :: 4 - Beta
Classifier: Programming Language :: Python :: 3.7
Classifier: License :: OSI Approved :: Apache Software License
Requires-Python: >=3.7
Requires-Dist: SQLAlchemy <3.0,>=1.3.17
Requires-Dist: packaging <24.0,>=21.3
Provides-Extra: flask
Requires-Dist: flask ; extra == 'flask'
Requires-Dist: flask-sqlalchemy <3.0 ; extra == 'flask'
